llama_index/llms/neutrino/__init__.py
llama_index/llms/neutrino/base.py
llama_index_llms_neutrino-0.4.1.dist-info/METADATA
llama_index_llms_neutrino-0.4.1.dist-info/WHEEL
llama_index_llms_neutrino-0.4.1.dist-info/licenses/LICENSE
llama_index_llms_neutrino-0.4.1.dist-info/RECORD
